Workbook

Sheet Summary
A1: AtliQ Sales Memory Assistant: cost estimate
A2: Monthly cost to run the assistant for 3 founders + Jay (base case). Change blue cells on the Assumptions sheet; everything here updates.
B4: Metric | C4: Value | D4: What it means
B5: AI model cost per month | C5: ='Token Usage'!$L$11 -> 6.4799372 | D5: Haiku 5.5 for reading + Sonnet 5.5 for drafts (Token Usage sheet).
B6: Infrastructure per month | C6: =Infrastructure!$B$19 -> 85 | D6: Hosting, database, email sending, monitoring (Infrastructure sheet).
B7: Running cost per month (AI + infrastructure) | C7: =C5+C6 -> 91.479937 | D7: What it costs to keep the assistant switched on.
B8: Maintenance and weekly checks per month | C8: =Infrastructure!$B$20 -> 363.3 | D8: Developer upkeep + Jay's 30-minute weekly check.
B9: Total monthly cost | C9: =C7+C8 -> 454.77994 | D9: Running cost + people upkeep.
B10: One-time build cost | C10: =Infrastructure!$C$20 -> 7200 | D10: 180 developer hours (build + eval set).
B11: First-year cost | C11: =C10+12*C9 -> 12657.359 | D11: Build + 12 months.
B12: Cost per founder per month | C12: =IF(Assumptions!$B$7>0,C9/Assumptions!$B$7,0) -> 151.59331 | D12: Total monthly cost ÷ founders.
B13: AI cost per email processed | C13: =IF((Assumptions!$B$9+Assumptions!$B$10)>0,C5/((Assumptions!$B$9+Assumptions!$B$10)*Assumptions!$B$6),0) -> 0.0046022281 | D13: AI bill ÷ all emails and notes in the month.
B14: AI cost per draft reply | C14: ='Token Usage'!J9 -> 0.012904 | D14: One Sonnet 5.5 draft, including thinking.
B15: Tokens per month | C15: ='Token Usage'!$D$13 -> 6803412 | D15: All tasks, cached + fresh + answer + thinking.
B16: AI share of total monthly cost | C16: =IF(C9>0,C5/C9,0) -> 0.014248512 | D16: Shows where the money really goes.
B17: Cost per follow-up actioned on time (North Star) | C17: ='Value & ROI'!B22 -> 4.372884 | D17: Monthly cost ÷ follow-ups done on time at the 80% target.
B18: Time value created per month | C18: ='Value & ROI'!B17 -> 1244.622 | D18: Founder and Jay hours saved (Value & ROI sheet).
B19: Payback of build cost (time savings only) | C19: ='Value & ROI'!B20 -> 9.1157465 | D19: Pipeline upside (USD 200k revived) not counted.
B20: If every step used Opus 5.5 instead | C20: ='Token Usage'!N11 -> 30.697392 | D20: AI cost per month with the most capable Opus everywhere.
B22: Key takeaways
B23: ="1. The AI itself is cheap: about "&TEXT(C5,"$0")&" a month, or "&TEXT(C13,"$0.000")&" per email. It is "&TEXT(C16,"0%")&" of the total monthly cost." -> 1. The AI itself is cheap: about $6 a month, or $0.005 per email. It is 1% of the total monthly cost.
B24: ="2. People time (build and upkeep) is the real cost: build "&TEXT(C10,"$#,##0")&" once, then "&TEXT(C8,"$0")&" a month." -> 2. People time (build and upkeep) is the real cost: build $7,200 once, then $363 a month.
B25: ="3. Using the right model per task matters: Opus 5.5 everywhere would cost "&TEXT(C20,"$0")&" a month, about "&TEXT(IF(C5>0,C20/C5,0),"0")&"x the recommended mix." -> 3. Using the right model per task matters: Opus 5.5 everywhere would cost $31 a month, about 5x the recommended mix.
B26: ="4. Even at 3x volume the AI bill stays near "&TEXT(Scenarios!C7,"$0")&" a month, so cost does not limit growth; quality and trust do." -> 4. Even at 3x volume the AI bill stays near $19 a month, so cost does not limit growth; quality and trust do.
B27: ="5. The build pays back in about "&TEXT('Value & ROI'!B20,"0.0")&" months from time savings alone, before any revived pipeline." -> 5. The build pays back in about 9.1 months from time savings alone, before any revived pipeline.
B29: Legend: blue text = input you can change · black = formula · green = linked from another sheet · yellow fill = key assumption.

Sheet Assumptions
A1: Assumptions: volumes, sizes and rates
A2: Blue = input you can change. Yellow = key assumption. Every other sheet recalculates from these cells.
A4: Assumption | B4: Value | C4: Unit | D4: Why this number / source
A5: Team and calendar
A6: Working days per month | B6: 22 | C6: days | D6: Mon–Fri, about 22 a month.
A7: Founder-sellers using the daily brief | B7: 3 | C7: people | D7: Bhavin, Dhaval, Karandeep (dataset). Jay also gets a CRM-fix brief.
A8: Volumes (base case)
A9: Emails in the sales mailbox per day (in + out) | B9: 60 | C9: emails/day | D9: Assumption: ~20 sales emails a day per founder. The dataset is a sample of ~50 key threads, not the full mailbox.
A10: Meeting notes per day | B10: 4 | C10: notes/day | D10: Assumption: 1–2 client meetings per founder per day; about 4 notes get written up.
A11: Share removed by free rules before AI (newsletters, auto-replies, internal) | B11: 0.25 | C11: % of items | D11: Plain sender/folder rules cost nothing; only the rest reaches the AI.
A12: Share of triaged items that need extraction (real sales content) | B12: 0.5 | C12: % of triaged | D12: Assumption: half the sales folder is routine (scheduling, thanks, FYI).
A13: Share of extracted items needing an AI match check (close-call company names) | B13: 0.15 | C13: % of extracted | D13: Most items match the CRM by exact name or email domain; AI only checks the unclear ones.
A14: Draft replies per founder per day | B14: 5 | C14: drafts/day | D14: Brief is capped at 7 items; on an average day ~5 need a reply draft.
A15: Redraft rate (founder asks for a new version) | B15: 0.2 | C15: % of drafts | D15: Assumption: 1 in 5 drafts gets regenerated.
A16: Quality-check sample per week (AI judge for groundedness) | B16: 20 | C16: items/week | D16: From the PRD: weekly sample of 20 items to check facts against sources.
A17: Text size (measured from the dataset)
A18: Average words per email or note | B18: 127 | C18: words | D18: Measured: 51 dataset files, 6,470 words, average 127 (median 123, max 524).
A19: Thread multiplier (earlier replies quoted in the thread) | B19: 3 | C19: x | D19: Assumption: a real thread carries ~2 earlier messages along with the new one.
A20: Tokens per word | B20: 1.33 | C20: tokens/word | D20: Rule of thumb: 1 token ≈ ¾ of a word for English text.
A21: CRM context sent with each extraction or draft | B21: 600 | C21: tokens | D21: The CRM export is ~5.8 KB for 40 records (~1,500 tokens); we send only the 2–3 likely matching records.
A22: Cost levers
A23: Share of cached prompt tokens billed as a cache write | B23: 0.1 | C23: % of cached | D23: Fixed instructions are cached; the cache is re-written a few times a day (write = 1.25x input price).
A24: Use the Batch API for background steps? (Yes / No) | B24: No | C24: Yes/No | D24: Batch API is 50% cheaper but results can take longer to return. Off by default so the brief always uses fresh email; see Scenarios for the saving.
A25: Monthly AI spend alert threshold | B25: 50 | C25: USD/month | D25: Alert the team if AI spend passes this; well above the base estimate, so it only fires on a bug or a volume spike.
A26: People cost rates (for build, maintenance and value)
A27: Developer cost per hour | B27: 40 | C27: USD/hour | D27: Assumption: contract developer rate. Change to your real rate.
A28: Value of one founder hour | B28: 50 | C28: USD/hour | D28: Assumption: opportunity cost of founder selling time.
A29: Sales ops (Jay) cost per hour | B29: 20 | C29: USD/hour | D29: Assumption.

Sheet Model Prices
A1: Model prices (Anthropic API, USD per 1 million tokens)
A2: Source: Anthropic API list prices as of October 2026 (first-party API). Update if prices change.
A4: Model | B4: Input | C4: Output | D4: Cache read | E4: Best used for | F4: Note
A5: Claude Haiku 5.5 | B5: 0.1 | C5: 0.5 | D5: 0.01 | E5: High-volume reading: triage, extraction, match checks | F5: Price for prompts up to 100K tokens. Cache-read price assumed at 10% of input (standard ratio); not confirmed.
A6: Claude Sonnet 5.5 | B6: 2 | C6: 10 | D6: 0.2 | E6: Writing that a founder reads: draft replies, quality judge | F6: Cache read $0.20 per 1M.
A7: Claude Opus 5.5 | B7: 4 | C7: 20 | D7: 0.2 | E7: Comparison only (most capable Opus) | F7: Cache read $0.20 per 1M. Used in Scenarios to show the cost of "best model everywhere".
A9: Batch API discount | B9: 0.5 | C9: Background jobs sent through the Batch API are billed at 50% of the normal price.
A10: Cache write premium | B10: 1.25 | C10: Writing a prompt into the cache costs 1.25x the normal input price; reading it back costs the cache-read price.
A12: Thinking tokens | B12: These models think before answering. Thinking tokens are billed as output tokens, so the Token Usage sheet counts them separately. We run triage and extraction at low effort to keep thinking short.

Sheet Token Usage
A1: Token usage and model cost per AI task
A2: One row per AI call type. Calls per day come from Assumptions; tokens per call are estimates (blue). Cost columns are formulas.
A4: AI task | B4: Feature | C4: Model (pick) | D4: Calls per day | E4: Cached prompt tokens | F4: Fresh input tokens | G4: Answer tokens | H4: Thinking tokens | I4: Batch-eligible? | J4: Cost per call | K4: Cost per day | L4: Cost per month | M4: Month if all Sonnet 5.5 | N4: Month if all Opus 5.5 | O4: Month if all Haiku 5.5 | P4: What goes in / why this size
A5: 1. Triage | B5: All | C5: Claude Haiku 5.5 | D5: =(Assumptions!$B$9+Assumptions!$B$10)*(1-Assumptions!$B$11) -> 48 | E5: 1200 | F5: =ROUND(Assumptions!$B$18*Assumptions!$B$20,0)+100 -> 269 | G5: 60 | H5: 100 | I5: Yes | J5: =(E5*((1-Assumptions!$B$23)*INDEX('Model Prices'!$D$5:$D$7,MATCH(C5,'Model Prices'!$A$5:$A$7,0))+Assumptions!$B$23*'Model Prices'!$B$10*INDEX('Model Prices'!$B$5:$B$7,MATCH(C5,'Model Prices'!$A$5:$A$7,0)))+F5*INDEX('Model Prices'!$B$5:$B$7,MATCH(C5,'Model Prices'!$A$5:$A$7,0))+(G5+H5)*INDEX('Model Prices'!$C$5:$C$7,MATCH(C5,'Model Prices'!$A$5:$A$7,0)))/1000000*IF(AND(Assumptions!$B$24="Yes",I5="Yes"),'Model Prices'!$B$9,1) -> 0.0001327 | K5: =J5*D5 -> 0.0063696 | L5: =K5*Assumptions!$B$6 -> 0.1401312 | M5: =((E5*((1-Assumptions!$B$23)*INDEX('Model Prices'!$D$5:$D$7,MATCH("Claude Sonnet 5.5",'Model Prices'!$A$5:$A$7,0))+Assumptions!$B$23*'Model Prices'!$B$10*INDEX('Model Prices'!$B$5:$B$7,MATCH("Claude Sonnet 5.5",'Model Prices'!$A$5:$A$7,0)))+F5*INDEX('Model Prices'!$B$5:$B$7,MATCH("Claude Sonnet 5.5",'Model Prices'!$A$5:$A$7,0))+(G5+H5)*INDEX('Model Prices'!$C$5:$C$7,MATCH("Claude Sonnet 5.5",'Model Prices'!$A$5:$A$7,0)))/1000000*IF(AND(Assumptions!$B$24="Yes",I5="Yes"),'Model Prices'!$B$9,1))*D5*Assumptions!$B$6 -> 2.802624 | N5: =((E5*((1-Assumptions!$B$23)*INDEX('Model Prices'!$D$5:$D$7,MATCH("Claude Opus 5.5",'Model Prices'!$A$5:$A$7,0))+Assumptions!$B$23*'Model Prices'!$B$10*INDEX('Model Prices'!$B$5:$B$7,MATCH("Claude Opus 5.5",'Model Prices'!$A$5:$A$7,0)))+F5*INDEX('Model Prices'!$B$5:$B$7,MATCH("Claude Opus 5.5",'Model Prices'!$A$5:$A$7,0))+(G5+H5)*INDEX('Model Prices'!$C$5:$C$7,MATCH("Claude Opus 5.5",'Model Prices'!$A$5:$A$7,0)))/1000000*IF(AND(Assumptions!$B$24="Yes",I5="Yes"),'Model Prices'!$B$9,1))*D5*Assumptions!$B$6 -> 5.377152 | O5: =((E5*((1-Assumptions!$B$23)*INDEX('Model Prices'!$D$5:$D$7,MATCH("Claude Haiku 5.5",'Model Prices'!$A$5:$A$7,0))+Assumptions!$B$23*'Model Prices'!$B$10*INDEX('Model Prices'!$B$5:$B$7,MATCH("Claude Haiku 5.5",'Model Prices'!$A$5:$A$7,0)))+F5*INDEX('Model Prices'!$B$5:$B$7,MATCH("Claude Haiku 5.5",'Model Prices'!$A$5:$A$7,0))+(G5+H5)*INDEX('Model Prices'!$C$5:$C$7,MATCH("Claude Haiku 5.5",'Model Prices'!$A$5:$A$7,0)))/1000000*IF(AND(Assumptions!$B$24="Yes",I5="Yes"),'Model Prices'!$B$9,1))*D5*Assumptions!$B$6 -> 0.1401312 | P5: Is this email sales-related and does it need action? Instructions are cached; the new email (~170 tokens) + sender details are fresh. Output is a short label.
A6: 2. Extract facts + source quote | B6: F1, F2, F3, F4 | C6: Claude Haiku 5.5 | D6: =D5*Assumptions!$B$12 -> 24 | E6: 2500 | F6: =ROUND(Assumptions!$B$18*Assumptions!$B$19*Assumptions!$B$20,0)+Assumptions!$B$21 -> 1107 | G6: 450 | H6: 350 | I6: Yes | J6: =(E6*((1-Assumptions!$B$23)*INDEX('Model Prices'!$D$5:$D$7,MATCH(C6,'Model Prices'!$A$5:$A$7,0))+Assumptions!$B$23*'Model Prices'!$B$10*INDEX('Model Prices'!$B$5:$B$7,MATCH(C6,'Model Prices'!$A$5:$A$7,0)))+F6*INDEX('Model Prices'!$B$5:$B$7,MATCH(C6,'Model Prices'!$A$5:$A$7,0))+(G6+H6)*INDEX('Model Prices'!$C$5:$C$7,MATCH(C6,'Model Prices'!$A$5:$A$7,0)))/1000000*IF(AND(Assumptions!$B$24="Yes",I6="Yes"),'Model Prices'!$B$9,1) -> 0.00056445 | K6: =J6*D6 -> 0.0135468 | L6: =K6*Assumptions!$B$6 -> 0.2980296 | M6: =((E6*((1-Assumptions!$B$23)*INDEX('Model Prices'!$D$5:$D$7,MATCH("Claude Sonnet 5.5",'Model Prices'!$A$5:$A$7,0))+Assumptions!$B$23*'Model Prices'!$B$10*INDEX('Model Prices'!$B$5:$B$7,MATCH("Claude Sonnet 5.5",'Model Prices'!$A$5:$A$7,0)))+F6*INDEX('Model Prices'!$B$5:$B$7,MATCH("Claude Sonnet 5.5",'Model Prices'!$A$5:$A$7,0))+(G6+H6)*INDEX('Model Prices'!$C$5:$C$7,MATCH("Claude Sonnet 5.5",'Model Prices'!$A$5:$A$7,0)))/1000000*IF(AND(Assumptions!$B$24="Yes",I6="Yes"),'Model Prices'!$B$9,1))*D6*Assumptions!$B$6 -> 5.960592 | N6: =((E6*((1-Assumptions!$B$23)*INDEX('Model Prices'!$D$5:$D$7,MATCH("Claude Opus 5.5",'Model Prices'!$A$5:$A$7,0))+Assumptions!$B$23*'Model Prices'!$B$10*INDEX('Model Prices'!$B$5:$B$7,MATCH("Claude Opus 5.5",'Model Prices'!$A$5:$A$7,0)))+F6*INDEX('Model Prices'!$B$5:$B$7,MATCH("Claude Opus 5.5",'Model Prices'!$A$5:$A$7,0))+(G6+H6)*INDEX('Model Prices'!$C$5:$C$7,MATCH("Claude Opus 5.5",'Model Prices'!$A$5:$A$7,0)))/1000000*IF(AND(Assumptions!$B$24="Yes",I6="Yes"),'Model Prices'!$B$9,1))*D6*Assumptions!$B$6 -> 11.683584 | O6: =((E6*((1-Assumptions!$B$23)*INDEX('Model Prices'!$D$5:$D$7,MATCH("Claude Haiku 5.5",'Model Prices'!$A$5:$A$7,0))+Assumptions!$B$23*'Model Prices'!$B$10*INDEX('Model Prices'!$B$5:$B$7,MATCH("Claude Haiku 5.5",'Model Prices'!$A$5:$A$7,0)))+F6*INDEX('Model Prices'!$B$5:$B$7,MATCH("Claude Haiku 5.5",'Model Prices'!$A$5:$A$7,0))+(G6+H6)*INDEX('Model Prices'!$C$5:$C$7,MATCH("Claude Haiku 5.5",'Model Prices'!$A$5:$A$7,0)))/1000000*IF(AND(Assumptions!$B$24="Yes",I6="Yes"),'Model Prices'!$B$9,1))*D6*Assumptions!$B$6 -> 0.2980296 | P6: Pulls out leads, promises, questions, dates, each with its quote. Cached: instructions, output format, 3 examples. Fresh: the thread and 2–3 matching CRM records.
A7: 3. CRM match check | B7: F1 | C7: Claude Haiku 5.5 | D7: =D6*Assumptions!$B$13 -> 3.6 | E7: 1000 | F7: 800 | G7: 150 | H7: 150 | I7: Yes | J7: =(E7*((1-Assumptions!$B$23)*INDEX('Model Prices'!$D$5:$D$7,MATCH(C7,'Model Prices'!$A$5:$A$7,0))+Assumptions!$B$23*'Model Prices'!$B$10*INDEX('Model Prices'!$B$5:$B$7,MATCH(C7,'Model Prices'!$A$5:$A$7,0)))+F7*INDEX('Model Prices'!$B$5:$B$7,MATCH(C7,'Model Prices'!$A$5:$A$7,0))+(G7+H7)*INDEX('Model Prices'!$C$5:$C$7,MATCH(C7,'Model Prices'!$A$5:$A$7,0)))/1000000*IF(AND(Assumptions!$B$24="Yes",I7="Yes"),'Model Prices'!$B$9,1) -> 0.0002515 | K7: =J7*D7 -> 0.0009054 | L7: =K7*Assumptions!$B$6 -> 0.0199188 | M7: =((E7*((1-Assumptions!$B$23)*INDEX('Model Prices'!$D$5:$D$7,MATCH("Claude Sonnet 5.5",'Model Prices'!$A$5:$A$7,0))+Assumptions!$B$23*'Model Prices'!$B$10*INDEX('Model Prices'!$B$5:$B$7,MATCH("Claude Sonnet 5.5",'Model Prices'!$A$5:$A$7,0)))+F7*INDEX('Model Prices'!$B$5:$B$7,MATCH("Claude Sonnet 5.5",'Model Prices'!$A$5:$A$7,0))+(G7+H7)*INDEX('Model Prices'!$C$5:$C$7,MATCH("Claude Sonnet 5.5",'Model Prices'!$A$5:$A$7,0)))/1000000*IF(AND(Assumptions!$B$24="Yes",I7="Yes"),'Model Prices'!$B$9,1))*D7*Assumptions!$B$6 -> 0.398376 | N7: =((E7*((1-Assumptions!$B$23)*INDEX('Model Prices'!$D$5:$D$7,MATCH("Claude Opus 5.5",'Model Prices'!$A$5:$A$7,0))+Assumptions!$B$23*'Model Prices'!$B$10*INDEX('Model Prices'!$B$5:$B$7,MATCH("Claude Opus 5.5",'Model Prices'!$A$5:$A$7,0)))+F7*INDEX('Model Prices'!$B$5:$B$7,MATCH("Claude Opus 5.5",'Model Prices'!$A$5:$A$7,0))+(G7+H7)*INDEX('Model Prices'!$C$5:$C$7,MATCH("Claude Opus 5.5",'Model Prices'!$A$5:$A$7,0)))/1000000*IF(AND(Assumptions!$B$24="Yes",I7="Yes"),'Model Prices'!$B$9,1))*D7*Assumptions!$B$6 -> 0.782496 | O7: =((E7*((1-Assumptions!$B$23)*INDEX('Model Prices'!$D$5:$D$7,MATCH("Claude Haiku 5.5",'Model Prices'!$A$5:$A$7,0))+Assumptions!$B$23*'Model Prices'!$B$10*INDEX('Model Prices'!$B$5:$B$7,MATCH("Claude Haiku 5.5",'Model Prices'!$A$5:$A$7,0)))+F7*INDEX('Model Prices'!$B$5:$B$7,MATCH("Claude Haiku 5.5",'Model Prices'!$A$5:$A$7,0))+(G7+H7)*INDEX('Model Prices'!$C$5:$C$7,MATCH("Claude Haiku 5.5",'Model Prices'!$A$5:$A$7,0)))/1000000*IF(AND(Assumptions!$B$24="Yes",I7="Yes"),'Model Prices'!$B$9,1))*D7*Assumptions!$B$6 -> 0.0199188 | P7: Only for close calls (e.g. Meridian L-1003 vs L-1027). Compares the item with candidate records.
A8: 4. Brief intro line | B8: F5 | C8: Claude Haiku 5.5 | D8: =Assumptions!$B$7+1 -> 4 | E8: 800 | F8: 1500 | G8: 200 | H8: 100 | I8: No | J8: =(E8*((1-Assumptions!$B$23)*INDEX('Model Prices'!$D$5:$D$7,MATCH(C8,'Model Prices'!$A$5:$A$7,0))+Assumptions!$B$23*'Model Prices'!$B$10*INDEX('Model Prices'!$B$5:$B$7,MATCH(C8,'Model Prices'!$A$5:$A$7,0)))+F8*INDEX('Model Prices'!$B$5:$B$7,MATCH(C8,'Model Prices'!$A$5:$A$7,0))+(G8+H8)*INDEX('Model Prices'!$C$5:$C$7,MATCH(C8,'Model Prices'!$A$5:$A$7,0)))/1000000*IF(AND(Assumptions!$B$24="Yes",I8="Yes"),'Model Prices'!$B$9,1) -> 0.0003172 | K8: =J8*D8 -> 0.0012688 | L8: =K8*Assumptions!$B$6 -> 0.0279136 | M8: =((E8*((1-Assumptions!$B$23)*INDEX('Model Prices'!$D$5:$D$7,MATCH("Claude Sonnet 5.5",'Model Prices'!$A$5:$A$7,0))+Assumptions!$B$23*'Model Prices'!$B$10*INDEX('Model Prices'!$B$5:$B$7,MATCH("Claude Sonnet 5.5",'Model Prices'!$A$5:$A$7,0)))+F8*INDEX('Model Prices'!$B$5:$B$7,MATCH("Claude Sonnet 5.5",'Model Prices'!$A$5:$A$7,0))+(G8+H8)*INDEX('Model Prices'!$C$5:$C$7,MATCH("Claude Sonnet 5.5",'Model Prices'!$A$5:$A$7,0)))/1000000*IF(AND(Assumptions!$B$24="Yes",I8="Yes"),'Model Prices'!$B$9,1))*D8*Assumptions!$B$6 -> 0.558272 | N8: =((E8*((1-Assumptions!$B$23)*INDEX('Model Prices'!$D$5:$D$7,MATCH("Claude Opus 5.5",'Model Prices'!$A$5:$A$7,0))+Assumptions!$B$23*'Model Prices'!$B$10*INDEX('Model Prices'!$B$5:$B$7,MATCH("Claude Opus 5.5",'Model Prices'!$A$5:$A$7,0)))+F8*INDEX('Model Prices'!$B$5:$B$7,MATCH("Claude Opus 5.5",'Model Prices'!$A$5:$A$7,0))+(G8+H8)*INDEX('Model Prices'!$C$5:$C$7,MATCH("Claude Opus 5.5",'Model Prices'!$A$5:$A$7,0)))/1000000*IF(AND(Assumptions!$B$24="Yes",I8="Yes"),'Model Prices'!$B$9,1))*D8*Assumptions!$B$6 -> 1.103872 | O8: =((E8*((1-Assumptions!$B$23)*INDEX('Model Prices'!$D$5:$D$7,MATCH("Claude Haiku 5.5",'Model Prices'!$A$5:$A$7,0))+Assumptions!$B$23*'Model Prices'!$B$10*INDEX('Model Prices'!$B$5:$B$7,MATCH("Claude Haiku 5.5",'Model Prices'!$A$5:$A$7,0)))+F8*INDEX('Model Prices'!$B$5:$B$7,MATCH("Claude Haiku 5.5",'Model Prices'!$A$5:$A$7,0))+(G8+H8)*INDEX('Model Prices'!$C$5:$C$7,MATCH("Claude Haiku 5.5",'Model Prices'!$A$5:$A$7,0)))/1000000*IF(AND(Assumptions!$B$24="Yes",I8="Yes"),'Model Prices'!$B$9,1))*D8*Assumptions!$B$6 -> 0.0279136 | P8: One short opening summary per person (founders + Jay). Ranking itself is plain rules, not AI.
A9: 5. Draft reply | B9: F5 | C9: Claude Sonnet 5.5 | D9: =Assumptions!$B$7*Assumptions!$B$14*(1+Assumptions!$B$15) -> 18 | E9: 3000 | F9: =ROUND(Assumptions!$B$18*Assumptions!$B$19*Assumptions!$B$20,0)+Assumptions!$B$21+200 -> 1307 | G9: 300 | H9: 600 | I9: No | J9: =(E9*((1-Assumptions!$B$23)*INDEX('Model Prices'!$D$5:$D$7,MATCH(C9,'Model Prices'!$A$5:$A$7,0))+Assumptions!$B$23*'Model Prices'!$B$10*INDEX('Model Prices'!$B$5:$B$7,MATCH(C9,'Model Prices'!$A$5:$A$7,0)))+F9*INDEX('Model Prices'!$B$5:$B$7,MATCH(C9,'Model Prices'!$A$5:$A$7,0))+(G9+H9)*INDEX('Model Prices'!$C$5:$C$7,MATCH(C9,'Model Prices'!$A$5:$A$7,0)))/1000000*IF(AND(Assumptions!$B$24="Yes",I9="Yes"),'Model Prices'!$B$9,1) -> 0.012904 | K9: =J9*D9 -> 0.232272 | L9: =K9*Assumptions!$B$6 -> 5.109984 | M9: =((E9*((1-Assumptions!$B$23)*INDEX('Model Prices'!$D$5:$D$7,MATCH("Claude Sonnet 5.5",'Model Prices'!$A$5:$A$7,0))+Assumptions!$B$23*'Model Prices'!$B$10*INDEX('Model Prices'!$B$5:$B$7,MATCH("Claude Sonnet 5.5",'Model Prices'!$A$5:$A$7,0)))+F9*INDEX('Model Prices'!$B$5:$B$7,MATCH("Claude Sonnet 5.5",'Model Prices'!$A$5:$A$7,0))+(G9+H9)*INDEX('Model Prices'!$C$5:$C$7,MATCH("Claude Sonnet 5.5",'Model Prices'!$A$5:$A$7,0)))/1000000*IF(AND(Assumptions!$B$24="Yes",I9="Yes"),'Model Prices'!$B$9,1))*D9*Assumptions!$B$6 -> 5.109984 | N9: =((E9*((1-Assumptions!$B$23)*INDEX('Model Prices'!$D$5:$D$7,MATCH("Claude Opus 5.5",'Model Prices'!$A$5:$A$7,0))+Assumptions!$B$23*'Model Prices'!$B$10*INDEX('Model Prices'!$B$5:$B$7,MATCH("Claude Opus 5.5",'Model Prices'!$A$5:$A$7,0)))+F9*INDEX('Model Prices'!$B$5:$B$7,MATCH("Claude Opus 5.5",'Model Prices'!$A$5:$A$7,0))+(G9+H9)*INDEX('Model Prices'!$C$5:$C$7,MATCH("Claude Opus 5.5",'Model Prices'!$A$5:$A$7,0)))/1000000*IF(AND(Assumptions!$B$24="Yes",I9="Yes"),'Model Prices'!$B$9,1))*D9*Assumptions!$B$6 -> 10.006128 | O9: =((E9*((1-Assumptions!$B$23)*INDEX('Model Prices'!$D$5:$D$7,MATCH("Claude Haiku 5.5",'Model Prices'!$A$5:$A$7,0))+Assumptions!$B$23*'Model Prices'!$B$10*INDEX('Model Prices'!$B$5:$B$7,MATCH("Claude Haiku 5.5",'Model Prices'!$A$5:$A$7,0)))+F9*INDEX('Model Prices'!$B$5:$B$7,MATCH("Claude Haiku 5.5",'Model Prices'!$A$5:$A$7,0))+(G9+H9)*INDEX('Model Prices'!$C$5:$C$7,MATCH("Claude Haiku 5.5",'Model Prices'!$A$5:$A$7,0)))/1000000*IF(AND(Assumptions!$B$24="Yes",I9="Yes"),'Model Prices'!$B$9,1))*D9*Assumptions!$B$6 -> 0.2554992 | P9: Written in the founder's tone. Cached: instructions + sample past emails for style. Fresh: thread, CRM facts, the item. Medium effort, so more thinking.
A10: 6. Weekly quality judge | B10: Evals | C10: Claude Sonnet 5.5 | D10: =Assumptions!$B$16/5 -> 4 | E10: 1500 | F10: 1200 | G10: 300 | H10: 400 | I10: Yes | J10: =(E10*((1-Assumptions!$B$23)*INDEX('Model Prices'!$D$5:$D$7,MATCH(C10,'Model Prices'!$A$5:$A$7,0))+Assumptions!$B$23*'Model Prices'!$B$10*INDEX('Model Prices'!$B$5:$B$7,MATCH(C10,'Model Prices'!$A$5:$A$7,0)))+F10*INDEX('Model Prices'!$B$5:$B$7,MATCH(C10,'Model Prices'!$A$5:$A$7,0))+(G10+H10)*INDEX('Model Prices'!$C$5:$C$7,MATCH(C10,'Model Prices'!$A$5:$A$7,0)))/1000000*IF(AND(Assumptions!$B$24="Yes",I10="Yes"),'Model Prices'!$B$9,1) -> 0.010045 | K10: =J10*D10 -> 0.04018 | L10: =K10*Assumptions!$B$6 -> 0.88396 | M10: =((E10*((1-Assumptions!$B$23)*INDEX('Model Prices'!$D$5:$D$7,MATCH("Claude Sonnet 5.5",'Model Prices'!$A$5:$A$7,0))+Assumptions!$B$23*'Model Prices'!$B$10*INDEX('Model Prices'!$B$5:$B$7,MATCH("Claude Sonnet 5.5",'Model Prices'!$A$5:$A$7,0)))+F10*INDEX('Model Prices'!$B$5:$B$7,MATCH("Claude Sonnet 5.5",'Model Prices'!$A$5:$A$7,0))+(G10+H10)*INDEX('Model Prices'!$C$5:$C$7,MATCH("Claude Sonnet 5.5",'Model Prices'!$A$5:$A$7,0)))/1000000*IF(AND(Assumptions!$B$24="Yes",I10="Yes"),'Model Prices'!$B$9,1))*D10*Assumptions!$B$6 -> 0.88396 | N10: =((E10*((1-Assumptions!$B$23)*INDEX('Model Prices'!$D$5:$D$7,MATCH("Claude Opus 5.5",'Model Prices'!$A$5:$A$7,0))+Assumptions!$B$23*'Model Prices'!$B$10*INDEX('Model Prices'!$B$5:$B$7,MATCH("Claude Opus 5.5",'Model Prices'!$A$5:$A$7,0)))+F10*INDEX('Model Prices'!$B$5:$B$7,MATCH("Claude Opus 5.5",'Model Prices'!$A$5:$A$7,0))+(G10+H10)*INDEX('Model Prices'!$C$5:$C$7,MATCH("Claude Opus 5.5",'Model Prices'!$A$5:$A$7,0)))/1000000*IF(AND(Assumptions!$B$24="Yes",I10="Yes"),'Model Prices'!$B$9,1))*D10*Assumptions!$B$6 -> 1.74416 | O10: =((E10*((1-Assumptions!$B$23)*INDEX('Model Prices'!$D$5:$D$7,MATCH("Claude Haiku 5.5",'Model Prices'!$A$5:$A$7,0))+Assumptions!$B$23*'Model Prices'!$B$10*INDEX('Model Prices'!$B$5:$B$7,MATCH("Claude Haiku 5.5",'Model Prices'!$A$5:$A$7,0)))+F10*INDEX('Model Prices'!$B$5:$B$7,MATCH("Claude Haiku 5.5",'Model Prices'!$A$5:$A$7,0))+(G10+H10)*INDEX('Model Prices'!$C$5:$C$7,MATCH("Claude Haiku 5.5",'Model Prices'!$A$5:$A$7,0)))/1000000*IF(AND(Assumptions!$B$24="Yes",I10="Yes"),'Model Prices'!$B$9,1))*D10*Assumptions!$B$6 -> 0.044198 | P10: Checks a sample of extracted facts against their source sentence (groundedness and made-up facts).
A11: Total | D11: =SUM(D5:D10) -> 101.6 | K11: =SUM(K5:K10) -> 0.2945426 | L11: =SUM(L5:L10) -> 6.4799372 | M11: =SUM(M5:M10) -> 15.713808 | N11: =SUM(N5:N10) -> 30.697392 | O11: =SUM(O5:O10) -> 0.7856904 | P11: M–O show the same workload if every task used one model, to compare strategies.
A13: Tokens per month (all tasks) | D13: =SUMPRODUCT(D5:D10,E5:E10+F5:F10+G5:G10+H5:H10)*Assumptions!$B$6 -> 6803412 | E13: tokens / month, cached + fresh + answer + thinking

Sheet Infrastructure
A1: Infrastructure and people costs
A2: Monthly running costs and one-time build effort. All values are assumptions (blue) for a small team.
A4: Item | B4: Monthly (USD) | C4: One-time (USD) | D4: Notes
A5: Running infrastructure
A6: App hosting (small container / serverless jobs every 2 hours) | B6: 25 | C6: 0 | D6: Runs the read–extract–brief pipeline and the web view. Low traffic: 4 users.
A7: Database (small managed Postgres) | B7: 25 | C7: 0 | D7: Stores items, tasks, drafts, audit log (kept 12 months).
A8: Email access (shared mailbox API) | B8: 0 | C8: 0 | D8: Uses the existing Google Workspace / Microsoft 365 plan; no extra licence.
A9: CRM connection | B9: 0 | C9: 0 | D9: Uses the existing CRM API or CSV import; no extra licence assumed.
A10: Sending the daily brief (transactional email service) | B10: 15 | C10: 0 | D10: ~100 emails a month; entry-level plan.
A11: Logging, monitoring and cost alerts | B11: 15 | C11: 0 | D11: Error alerts and the monthly AI spend alert.
A12: Backups and file storage | B12: 5 | C12: 0 | D12: Database backups.
A13: People
A14: Build: pipeline, prompts, brief, CRM write-back | B14: 0 | C14: =160*Assumptions!$B$27 -> 6400 | D14: 160 developer hours (about 4 weeks for one developer), from the PRD rollout plan.
A15: Build: evaluation set from the dataset | B15: 0 | C15: =20*Assumptions!$B$27 -> 800 | D15: 20 hours to label the test cases (missing leads, ByteBridge, FinEdge, Meridian duplicate).
A16: Maintenance: prompt tuning, fixes, model updates | B16: =8*Assumptions!$B$27 -> 320 | C16: 0 | D16: 8 developer hours a month.
A17: Weekly manual check of 20 emails (Jay) | B17: =0.5*4.33*Assumptions!$B$29 -> 43.3 | C17: 0 | D17: 30 minutes a week of Jay's time to catch what the AI missed (PRD section 12.3).
A19: Infrastructure total | B19: =SUM(B6:B12) -> 85 | C19: =SUM(C6:C12) -> 0
A20: People total | B20: =SUM(B14:B17) -> 363.3 | C20: =SUM(C14:C17) -> 7200

Sheet Value & ROI
A1: Value and payback
A2: What the cost buys. Time savings come from the PRD; pipeline upside is shown separately because it is less certain.
A4: Item | B4: Value | C4: Unit | D4: Notes
A5: Inputs
A6: Pipeline reviews per month | B6: 4.33 | C6: reviews | D6: Weekly pipeline review.
A7: Jay's hours saved per review | B7: 1.67 | C7: hours | D7: PRD target: CRM clean-up from ~2 hours to 20 minutes.
A8: Founder minutes saved per working day (each) | B8: 20 | C8: minutes | D8: Assumption: no retyping into the CRM and no hunting through the inbox for what is owed.
A9: Follow-ups due per month | B9: 130 | C9: follow-ups | D9: PRD worked example: ~30 a week.
A10: Target on-time rate (North Star) | B10: 0.8 | C10: % | D10: PRD target after 8 weeks.
A11: Stalled pipeline revived in 90 days | B11: 200000 | C11: USD | D11: PRD target: USD 200k of the USD 405k stalled.
A12: Win rate on revived deals | B12: 0.25 | C12: % | D12: Assumption.
A13: Gross margin on services | B13: 0.4 | C13: % | D13: Assumption.
A14: Results
A15: Jay's time saved per month | B15: =B6*B7*Assumptions!$B$29 -> 144.622 | C15: USD/month | D15: Hours saved x Jay's hourly cost.
A16: Founders' time saved per month | B16: =B8/60*Assumptions!$B$6*Assumptions!$B$7*Assumptions!$B$28 -> 1100 | C16: USD/month | D16: Minutes saved x days x founders x founder hourly value.
A17: Total time value per month | B17: =B15+B16 -> 1244.622 | C17: USD/month
A18: Total monthly cost (running + maintenance) | B18: =Summary!$C$9 -> 454.77994 | C18: USD/month | D18: From Summary.
A19: Net monthly value (time only) | B19: =B17-B18 -> 789.84206 | C19: USD/month
A20: Payback of the build cost (time savings only) | B20: =IF(B19>0,Infrastructure!$C$20/B19,"n/a") -> 9.1157465 | C20: months | D20: Build cost ÷ net monthly value.
A21: Pipeline upside: gross profit from revived deals (one-off) | B21: =B11*B12*B13 -> 20000 | C21: USD | D21: Revived value x win rate x margin. Not counted in payback above.
A22: Cost per follow-up actioned on time | B22: =IF(B9*B10>0,B18/(B9*B10),0) -> 4.372884 | C22: USD | D22: Ties cost to the North Star: monthly cost ÷ on-time follow-ups.

Sheet Scenarios
A1: Scenarios: volume and model strategy
A2: How the monthly AI bill changes with volume and with the choice of model. AI cost grows in line with volume.
A4: Volume scenario | B4: Volume multiplier | C4: Recommended mix | D4: Mix + Batch API | E4: All Sonnet 5.5 | F4: All Opus 5.5
A5: Low: quiet month | B5: 0.5 | C5: ='Token Usage'!$L$11*B5 -> 3.2399686 | D5: =('Token Usage'!$L$11-(SUMPRODUCT(('Token Usage'!I5:I10="Yes")*'Token Usage'!L5:L10)*IF(Assumptions!$B$24="Yes",0,1-'Model Prices'!$B$9)))*B5 -> 2.9044587 | E5: ='Token Usage'!$M$11*B5 -> 7.856904 | F5: ='Token Usage'!$N$11*B5 -> 15.348696
A6: Base: today's team | B6: 1 | C6: ='Token Usage'!$L$11*B6 -> 6.4799372 | D6: =('Token Usage'!$L$11-(SUMPRODUCT(('Token Usage'!I5:I10="Yes")*'Token Usage'!L5:L10)*IF(Assumptions!$B$24="Yes",0,1-'Model Prices'!$B$9)))*B6 -> 5.8089174 | E6: ='Token Usage'!$M$11*B6 -> 15.713808 | F6: ='Token Usage'!$N$11*B6 -> 30.697392
A7: High: team grows to ~10 sellers | B7: 3 | C7: ='Token Usage'!$L$11*B7 -> 19.439812 | D7: =('Token Usage'!$L$11-(SUMPRODUCT(('Token Usage'!I5:I10="Yes")*'Token Usage'!L5:L10)*IF(Assumptions!$B$24="Yes",0,1-'Model Prices'!$B$9)))*B7 -> 17.426752 | E7: ='Token Usage'!$M$11*B7 -> 47.141424 | F7: ='Token Usage'!$N$11*B7 -> 92.092176
A9: Reading the table
A10: Each cell is the AI model bill per month (USD). "Recommended mix" is Haiku 5.5 for reading and Sonnet 5.5 for drafts. "Mix + Batch API" sends background steps through the Batch API at half price. "All Opus 5.5" is the most capable Opus on every step.
A13: Full monthly cost (base volume) | B13: AI models | C13: Infrastructure | D13: Maintenance + checks | E13: Total | F13: AI share
A14: Recommended mix | B14: =C6 -> 6.4799372 | C14: =Infrastructure!$B$19 -> 85 | D14: =Infrastructure!$B$20 -> 363.3 | E14: =SUM(B14:D14) -> 454.77994 | F14: =IF(E14>0,B14/E14,0) -> 0.014248512
A15: Mix + Batch API | B15: =D6 -> 5.8089174 | C15: =Infrastructure!$B$19 -> 85 | D15: =Infrastructure!$B$20 -> 363.3 | E15: =SUM(B15:D15) -> 454.10892 | F15: =IF(E15>0,B15/E15,0) -> 0.012791903
A16: All Sonnet 5.5 | B16: =E6 -> 15.713808 | C16: =Infrastructure!$B$19 -> 85 | D16: =Infrastructure!$B$20 -> 363.3 | E16: =SUM(B16:D16) -> 464.01381 | F16: =IF(E16>0,B16/E16,0) -> 0.033864958
A17: All Opus 5.5 | B17: =F6 -> 30.697392 | C17: =Infrastructure!$B$19 -> 85 | D17: =Infrastructure!$B$20 -> 363.3 | E17: =SUM(B17:D17) -> 478.99739 | F17: =IF(E17>0,B17/E17,0) -> 0.064086762

Sheet Scope Decisions
A1: How cost shaped the scope
A2: Each decision below keeps the bill small and predictable. Figures are live formulas from the other sheets.
A4: Decision | B4: Cost effect | C4: Why it is also good for the product
A5: Use Haiku 5.5 for the high-volume reading (triage, extraction, match checks) | B5: ="Reading tasks cost "&TEXT(SUM('Token Usage'!L5:L7),"$0.00")&" a month on Haiku vs "&TEXT(SUM('Token Usage'!N5:N7),"$0.00")&" on Opus 5.5" -> Reading tasks cost $0.46 a month on Haiku vs $17.84 on Opus 5.5 | C5: Extraction is a well-defined task with a fixed output format; quality is checked by the eval set before launch.
A6: Use Sonnet 5.5 only for draft replies and the quality judge | B6: ="Drafts are "&TEXT('Token Usage'!L9/'Token Usage'!L11,"0%")&" of the AI bill, so this is where a stronger model is worth paying for" -> Drafts are 79% of the AI bill, so this is where a stronger model is worth paying for | C6: Drafts are what founders read and send; tone and accuracy matter most here.
A7: Rank the brief and set dates with plain rules, not AI | B7: ="$0 in tokens" -> $0 in tokens | C7: Founders can see why an item is on top; dates are predictable.
A8: Filter newsletters and auto-replies with free rules before any AI call | B8: ="Removes "&TEXT(Assumptions!$B$11,"0%")&" of items before they cost anything" -> Removes 25% of items before they cost anything | C8: Less noise in the brief.
A9: Cache the fixed instructions and examples (prompt caching) | B9: ="Cached tokens are billed at about 10% of the normal input price" -> Cached tokens are billed at about 10% of the normal input price | C9: Same instructions every time, so answers are consistent.
A10: Cap the brief at 7 items and draft only for brief items, not every email | B10: ="Limits drafts to "&TEXT('Token Usage'!D9,"0")&" a day across the team" -> Limits drafts to 18 a day across the team | C10: A short brief gets read; a long one gets ignored.
A11: Quality judge on a weekly sample of 20, not on every item | B11: ="Judge costs "&TEXT('Token Usage'!L10,"$0.00")&" a month" -> Judge costs $0.88 a month | C11: Enough to track groundedness weekly.
A12: No meeting bot or call transcription | B12: ="Avoids audio transcription and per-meeting bot costs" -> Avoids audio transcription and per-meeting bot costs | C12: Also avoids privacy and client-consent risk (PRD non-goal).
A13: Batch API kept as an option, off by default | B13: ="Turning it on saves about "&TEXT(Scenarios!C6-Scenarios!D6,"$0.00")&" a month" -> Turning it on saves about $0.67 a month | C13: Fresh email in the 8 am brief matters more than this saving.
A14: Monthly spend alert and a max-tokens cap on every call | B14: ="Alert fires above "&TEXT(Assumptions!$B$25,"$0")&" a month" -> Alert fires above $50 a month | C14: Catches a bug (e.g. a loop re-reading the mailbox) before it costs real money.
